discord_config/__init__.py
discord_config/dw.py
discord_config-0.0.2.dist-info/DESCRIPTION.rst
discord_config-0.0.2.dist-info/METADATA
discord_config-0.0.2.dist-info/RECORD
discord_config-0.0.2.dist-info/WHEEL
discord_config-0.0.2.dist-info/metadata.json
discord_config-0.0.2.dist-info/top_level.txt
