Metadata-Version: 2.0
Name: discord-config
Version: 0.0.2
Summary: Easy config module for Discord bots
Home-page: https://github.com/nowakcasimir/discord-config
Author: Casimir Nowak
Author-email: nowakcasimir@outlook.com
License: MIT
Platform: UNKNOWN
Classifier: Programming Language :: Python :: 3
Classifier: License :: OSI Approved :: MIT License
Classifier: Operating System :: OS Independent
Requires-Dist: appdirs
